mkdocs_timetoread_plugin/__init__.py
mkdocs_timetoread_plugin/plugin.py
mkdocs_timetoread_plugin-0.0.4.dist-info/LICENSE
mkdocs_timetoread_plugin-0.0.4.dist-info/METADATA
mkdocs_timetoread_plugin-0.0.4.dist-info/WHEEL
mkdocs_timetoread_plugin-0.0.4.dist-info/entry_points.txt
mkdocs_timetoread_plugin-0.0.4.dist-info/top_level.txt
mkdocs_timetoread_plugin-0.0.4.dist-info/RECORD
